auth/constants.py
auth/rhoas_auth.py
kafka_instance_sdk/__init__.py
kafka_mgmt_sdk/__init__.py
registry_instance_sdk/__init__.py
registry_mgmt_sdk/__init__.py
service_accounts_mgmt_sdk/__init__.py
smart_events_mgmt_sdk/__init__.py
jack_rhoas_sdks-0.0.6.dist-info/METADATA
jack_rhoas_sdks-0.0.6.dist-info/WHEEL
jack_rhoas_sdks-0.0.6.dist-info/RECORD
