Metadata-Version: 2.1
Name: jack-rhoas-sdks
Version: 0.0.6
Summary: A package which includes RHOAS SDKs
License: Apache License
Author: jackdelahunt
Author-email: jdelahun@redhat.com
Requires-Python: >=3.9,<4.0
Classifier: License :: Other/Proprietary License
Classifier: Programming Language :: Python :: 3
Classifier: Programming Language :: Python :: 3.9
Classifier: Programming Language :: Python :: 3.10
Classifier: Programming Language :: Python :: 3.11
Requires-Dist: microsoft-kiota-abstractions
Requires-Dist: microsoft-kiota-http
Requires-Dist: microsoft-kiota-serialization-json
Requires-Dist: microsoft-kiota-serialization-text
Requires-Dist: python-keycloak (>=2.5.0,<3.0.0)
